sendeventonroids/LICENSE.txt
sendeventonroids/README.MD
sendeventonroids/__init__.py
sendeventonroids/commandos.py
sendeventonroids/requirements.txt
sendeventonroids/thirdparty.json
sendeventonroids-0.10.dist-info/LICENSE.rst
sendeventonroids-0.10.dist-info/METADATA
sendeventonroids-0.10.dist-info/WHEEL
sendeventonroids-0.10.dist-info/top_level.txt
sendeventonroids-0.10.dist-info/RECORD
