Metadata-Version: 2.1
Name: sendeventonroids
Version: 0.10
Summary: sendevent without using sendevent - Android
Home-page: https://github.com/hansalemaos/sendeventonroids
Author: Johannes Fischer
Author-email: aulasparticularesdealemaosp@gmail.com
License: MIT
Keywords: android,adb,sendevent
Classifier: Development Status :: 4 - Beta
Classifier: Programming Language :: Python :: 3 :: Only
Classifier: Programming Language :: Python :: 3.10
Classifier: Topic :: Software Development :: Libraries :: Python Modules
Classifier: Topic :: Utilities
License-File: LICENSE.rst
Requires-Dist: adbshellexecuter
Requires-Dist: cythoncubicspline
